{
    "skills": [
        "Controls",
        "International",
        "Teaching",
        "Improvement",
        "Budget",
        "English",
        "Retail",
        "Research",
        "Word",
        "Safety",
        "Reports",
        "Illustrator",
        "Photoshop",
        "Cuisine",
        "Inventory",
        "Communication",
        "Spanish",
        "Operations",
        "Budgeting",
        "Ordering",
        "Publishing",
        "Training",
        "Analysis",
        "Microsoft word",
        "Sales",
        "Health"
    ],
    "experience": [
        "04/2016 to Current",
        "Chef Instructor Company Name \u00ef\u00bc\u200b City , State",
        "Teaching classes to small and large groups."
    ],
    "company_names": null,
    "total_experience": 0.0,
    "education": [],
    "category": "Summary Pastry"
}