{
    "skills": [
        "Partnership",
        "Responses",
        "Networking",
        "Budgeting",
        "Accounting",
        "Coding",
        "System",
        "Excel",
        "Strategy",
        "Sales",
        "Finance",
        "Communication",
        "P",
        "International",
        "Documentation",
        "Analysis",
        "Financial reports",
        "Business management",
        "Payroll",
        "Process",
        "Research",
        "Reconciliation",
        "Reports",
        "Audit",
        "Marketing",
        "Reporting",
        "Deposits"
    ],
    "experience": [
        "Accountant",
        "July 2012 to October 2015 Company Name \u00ef\u00bc\u200b City , State",
        "I have worked at Shantilal Gala & Company (Nairobi, Kenya) which is an Audit firm, since 2nd July 2012.",
        "I was employed as an Accountant in the Firm.",
        "Maintained accounts receivable documentation electronically and on paper.",
        "Processed bank reconciliations and financial reports to verify practice of p weekly and monthly.",
        "Increased efficiency and alleviated work loads by creating a new Excel financial recording system.",
        "Collaborated extensively with auditors during preliminary and year-end audit processes.",
        "Entered weekly sales and customer count sheets for review by management.",
        "Processed payroll, electronic deposits and employee pay adjustments.",
        "Collaborated extensively with auditors during preliminary and year-end audit processes."
    ],
    "company_names": null,
    "total_experience": 3.25,
    "education": [
        {
            "Degree": "Bachelor of",
            "Institution": "Summary\nFinancial Accountant specializing in financial planning, reporting and analysis in both private and public"
        },
        {
            "Degree": "Bachelor's degree",
            "Institution": "Highlights\nPeriodic financial reporting expert\nInvoice coding familiarity\nStrong communication skills\nGeneral ledger accounting skills\nComplex problem solving\nAccount reconciliation expert\nExperience\nAccountant\n \nJuly 2012\n \nto \nOctober 2015\n \nCompany Name"
        }
    ],
    "category": "ACCOUNTANT Summary"
}