{
    "skills": [
        "Engineering",
        "Windows",
        "Assembly",
        "Powerpoint",
        "Change management",
        "Purchasing",
        "Cms",
        "Supervisor",
        "Lean",
        "Drafting",
        "Sharepoint",
        "Inventory",
        "Administration",
        "Scheduling",
        "Access",
        "Word",
        "Reports",
        "Plan",
        "Testing",
        "System",
        "Six sigma",
        "Electronics",
        "Schedule",
        "Process",
        "Erp",
        "Research",
        "Installation",
        "Adobe",
        "Vendors",
        "Excel",
        "Autocad",
        "Documentation",
        "Iso"
    ],
    "experience": [
        "environments. MRP/ ERP systems include WDS, Syteline, Microsoft Great Plains, and others."
    ],
    "company_names": null,
    "total_experience": 0.0,
    "education": [
        {
            "Degree": "Bachelor of",
            "Institution": "PLANNING MANAGER\nExperience\nEngineering Planning Manager\n \nMay 2015\n \nto \nAugust 2017\n \nCompany Name"
        }
    ],
    "category": "Experience Engineering"
}