{
    "skills": [
        "Schedule",
        "R",
        "Technical",
        "Inventory management",
        "Policies",
        "Quickbooks",
        "Reporting",
        "Administration",
        "Accounting",
        "Retention",
        "Reconciliation",
        "Standard operating procedures",
        "Sales",
        "Receivables",
        "Continuous improvement",
        "Database",
        "Quality management",
        "Documentation",
        "Video",
        "Filing",
        "Engineering",
        "Payroll",
        "Specifications",
        "Purchasing",
        "Compliance",
        "Requests",
        "Operations",
        "Distribution",
        "Improvement",
        "Data entry",
        "Event planning",
        "Process",
        "Inventory",
        "Presentations",
        "Regulations",
        "Customer service",
        "Circuits",
        "Accounts payable",
        "Spreadsheets",
        "Microsoft office suite",
        "Invoices",
        "Reports",
        "Training",
        "Invoicing",
        "Travel",
        "Ordering",
        "System"
    ],
    "experience": [
        "Document Controller (Contract Position)",
        "April 2016 to May 2016 Company Name \u00ef\u00bc\u200b City , State",
        "Administration of the document control system.",
        "Ensure the accuracy of the change orders including but not limited to documentation, revisions, and required approvers.",
        "Examine documents to verify compliance, completeness, and accuracy of data.",
        "Control document database of all documentation that will allow secure document retention and corresponding files.",
        "Perform clerical duties to generate documents as necessary.",
        "Support continuous improvement activities in terms of process and system improvement."
    ],
    "company_names": null,
    "total_experience": 0.08,
    "education": [
        {
            "Degree": "master files,",
            "Institution": "CONTROLLER (CONTRACT POSITION)\nSummary\nDedicated and technically skilled business professional with a versatile administrative support skill set developed through experience as an Office\nManager, Customer Service Representative, Administrative Assistant and Buyer\nHighlights\nOffice Management\nTeam Building & Supervision\nStaff Development & Training\nPolicies & Procedures Manuals\nReport & Document Preparation\nSpreadsheet & Database Creation\nAccounts Payable"
        }
    ],
    "category": "CONTRACT POSITION"
}