{
    "skills": [
        "Schedule",
        "Adobe",
        "Design",
        "Adobe creative suite",
        "Facebook",
        "Analyze",
        "Graphic design",
        "Inventory management",
        "Reporting",
        "Administration",
        "Research",
        "Fundraising",
        "Sales",
        "Finance",
        "Database",
        "Strategy",
        "Budget",
        "Writing",
        "Engagement",
        "Payments",
        "Marketing",
        "Updates",
        "Twitter",
        "Administrative support",
        "Higher education",
        "Retail",
        "Operations",
        "Wordpress",
        "Email",
        "Event planning",
        "Process",
        "Inventory",
        "Customer service",
        "Content",
        "Healthcare",
        "Scheduling",
        "Contracts",
        "Microsoft office suite",
        "Transactions",
        "Analytics",
        "Training",
        "Marketing strategy",
        "Security",
        "System",
        "Visual"
    ],
    "experience": [
        "Director of Community",
        "August 2017 to Current Company Name \u00ef\u00bc\u200b City , State"
    ],
    "company_names": null,
    "total_experience": 0.0,
    "education": [
        {
            "Degree": "master\n \nJuly",
            "Institution": "OF COMMUNITY\nSkills\nAdobe Creative Suite, Microsoft Office Suite, Google Apps, Facebook, Twitter, Instagram, Pinterest, Tumblr"
        }
    ],
    "category": "Adobe Creative"
}