{
    "skills": [
        "Ui",
        "Engineering",
        "Transport",
        "Troubleshooting",
        "Training",
        "Solidworks",
        "Assembly",
        "Programming",
        "Lifecycle",
        "Instrumentation",
        "Drafting",
        "Analytical",
        "Communication",
        "Analysis",
        "English",
        "Os",
        "Matlab",
        "Schematics",
        "Algorithms",
        "Design",
        "French",
        "Hardware",
        "Testing",
        "System",
        "Electronics",
        "Process",
        "Technical",
        "Modeling",
        "Research",
        "C++",
        "Risk assessment",
        "Circuits",
        "Logistics",
        "Controls",
        "Audio",
        "Autocad",
        "Technical skills",
        "C",
        "Visual",
        "Robot",
        "Electrical",
        "Data entry"
    ],
    "experience": [
        "Company Name July 2015",
        "Conducted a successful research project on innovative use of Active Noise Control (ANC), 3-D Noise Mapping and Passive Noise",
        "Control systems as a solution for acoustical noise control issues in fast growing cities.",
        "Company Name October 2014",
        "Successfully engineered a new transmission line to feed a new load in a city's transmission system using PowerWorld simulation software,",
        "and ETAP.",
        "Performed Three-Phase Power Systems circuit analysis of the new system.",
        "Performed cost analysis and allocation for the project.",
        "Company Name September 2014 to August 2015 Engineering Intern",
        "Lead AutoCAD Drafting team of 3 in drafting 2D maps of Oil and Gas production sites.",
        "Contributed in building Spill Prevention, Control and Countermeasure (SPCC) plans for Oil and Gas Production Facilities, data entry, and",
        "various office duties assigned by my manager."
    ],
    "company_names": null,
    "total_experience": 0.92,
    "education": [
        {
            "Degree": "Master of",
            "Institution": "INTERN\nProfile\nProficient Entry Level Electrical Engineer with excellent technical, analytical and communication"
        },
        {
            "Degree": "Bachelor of",
            "Institution": "Willing to relocate anywhere in the"
        }
    ],
    "category": "Testing |"
}