{
    "skills": [
        "Recruitment",
        "Hris",
        "Updates",
        "Process",
        "Investigation",
        "Compliance",
        "Regulatory",
        "Testing",
        "Reports",
        "Administration",
        "Certification",
        "Regulations",
        "Employee relations",
        "Human resource",
        "Presentations",
        "Database",
        "Partnerships",
        "Staffing",
        "Recruiting",
        "Counsel",
        "Event planning",
        "Investigations",
        "Human resources",
        "Reporting",
        "Training",
        "Healthcare",
        "Licensing",
        "Budget",
        "Hospital"
    ],
    "experience": [
        "Company Name January 2014 to Current HR Coordinator"
    ],
    "company_names": null,
    "total_experience": 0.0,
    "education": [
        {
            "Degree": "MBA",
            "Institution": "COORDINATOR\nSummary\nApplicant Screening, Background Checks, Benefits Administration, Compliance, Compensation, Drug Testing, EEO Inquiries, Employee\nRelations, Event Planning"
        }
    ],
    "category": "COORDINATOR Summary"
}