{
    "skills": [
        "Ibm",
        "Schedule",
        "Design",
        "Queries",
        "Billing",
        "Budgeting",
        "Installation",
        "Accounting",
        "Database",
        "Pharmacy",
        "Tax",
        "System",
        "Excel",
        "Inventory",
        "Business development",
        "Vendors",
        "Access",
        "Mathematics",
        "Accounts receivable",
        "Sales",
        "Program development",
        "Hardware",
        "Accounts payable",
        "Gaap",
        "Security",
        "Specifications",
        "Bank reconciliation",
        "Documentation",
        "Technical",
        "Spreadsheets",
        "General ledger",
        "Payroll",
        "Reconciliation",
        "Consulting",
        "Supervisor",
        "Reports",
        "Banking",
        "Financial statements",
        "Marketing",
        "Invoicing",
        "Reporting",
        "Training"
    ],
    "experience": [
        "Consulted with customers to determine special needsand modified software accordingly.",
        "Backup to the support department in providing installation, training and telephone assistance to customers.",
        "Assisted the sales department with demonstrations and technical questions.",
        "Wrote software documentation.",
        "Designed Payroll tax calculation program to accommodate tax withholding for majority of states Instrumental in design of Order Entry",
        "application.",
        "01/1980 to 01/1981",
        "Staff Accountant Company Name \u00ef\u00bc\u200b City , State",
        "Bank with headquarters in Minneapolis, MN that later merged with Wells Fargo & Co.",
        "Responsible for the preparation of month-end financial statements, quarterly Call Reports and internal reports.",
        "Balanced or monitored the balancing of all subsidiary ledgers to general ledger on a monthly basis.",
        "Reviewed income and expense accounts for proper classification.",
        "Wrote BASIC computer programs.",
        "Participated in the bank's business development program."
    ],
    "company_names": null,
    "total_experience": 0.0,
    "education": [
        {
            "Degree": "Bachelor of",
            "Institution": "Summary\nSeveral years experience in providing information and creating software solutions for business needs and"
        }
    ],
    "category": "ACCOUNTANT Summary"
}