{
    "skills": [
        "Controls",
        "Computer science",
        "Billing",
        "System",
        "Transactions",
        "Process",
        "C",
        "Reconcile",
        "General ledger",
        "Word",
        "Research",
        "Excel",
        "Presentation",
        "Reports",
        "Presentations",
        "Communication",
        "Database",
        "Counsel",
        "Operations",
        "Access",
        "Policies",
        "Requests",
        "Client relationships",
        "Training",
        "Supervisor",
        "Budget",
        "Cisco",
        "Finance"
    ],
    "experience": [
        "Company Name City , State Finance Operations/ Supervisor Manager 09/1999 to 02/2012",
        "Company Name City , State Customer Relations Manager 03/2012 to Current",
        "Supervise and manage the daily operations of employees."
    ],
    "company_names": null,
    "total_experience": 0.0,
    "education": [],
    "category": "Professional Summary"
}