{
    "skills": [
        "System",
        "International",
        "Business development",
        "Process",
        "Project management",
        "Cpr",
        "Drafting",
        "Construction",
        "Plan",
        "Technical",
        "Engineering",
        "Consulting",
        "Statistics",
        "Reports",
        "Administration",
        "Retention",
        "Employee relations",
        "Business management",
        "Communication",
        "Gis",
        "Specifications",
        "Revenue growth",
        "Design",
        "Operations",
        "Scheduling",
        "Human resources",
        "Networking",
        "Training",
        "Deposits",
        "Autocad"
    ],
    "experience": [
        "Created maps, task lists, materials list, network contact logs, including vital daily interaction/ communication with foreman and laborers alike.",
        "03/2012 to 07/2016",
        "Assistant General Manager Company Name \u00ef\u00bc\u200b City , State"
    ],
    "company_names": null,
    "total_experience": 0.0,
    "education": [
        {
            "Degree": "Master's",
            "Institution": "DEVELOPMENT CONSULTANT\nSummary\nDiverse"
        },
        {
            "Degree": "Bachelor of",
            "Institution": "Planning & Development, Construction, Project Development with technical experience using AutoCAD & GIS"
        }
    ],
    "category": "CONSTRUCTION DEVELOPMENT"
}