{
    "skills": [
        "Engineering",
        "Ms project",
        "Process improvements",
        "Training",
        "Program management",
        "Product quality",
        "Assembly",
        "Green",
        "Engagement",
        "Programming",
        "Change management",
        "Supervisor",
        "Lifecycle",
        "Schedules",
        "Lean",
        "Analyze",
        "Analytical",
        "Procurement",
        "Analysis",
        "Staffing",
        "Administration",
        "Business strategy",
        "Retention",
        "Scheduling",
        "Experiments",
        "Marketing",
        "Metrics",
        "Design",
        "Strategy",
        "Spreadsheets",
        "Plan",
        "Fabrication",
        "Hardware",
        "Certification",
        "System",
        "Process improvement",
        "Schedule",
        "Project management",
        "Process",
        "Erp",
        "Forecasts",
        "Sourcing",
        "Product marketing",
        "Operations",
        "Installation",
        "Improvement"
    ],
    "experience": null,
    "company_names": null,
    "total_experience": 0,
    "education": [
        {
            "Degree": "MBA",
            "Institution": "INDUSTRIAL ENGINEERING MANAGER\nProfessional Summary"
        },
        {
            "Degree": "Bachelor",
            "Institution": "Industrial Engineer, Project Manager and Team Leader dedicated to boosting company revenue\nthrough exceptional leadership and rigorous cost and schedule control"
        }
    ],
    "category": "INDUSTRIAL ENGINEERING"
}